LICENSE
MANIFEST.in
README.md
pyproject.toml
setup.py
influxdb2_dbapi/__init__.py
influxdb2_dbapi/__version__.py
influxdb2_dbapi/console.py
influxdb2_dbapi/db.py
influxdb2_dbapi/exceptions.py
influxdb2_dbapi/influxdb2_sqlalchemy.py
influxdb2_dbapi.egg-info/PKG-INFO
influxdb2_dbapi.egg-info/SOURCES.txt
influxdb2_dbapi.egg-info/dependency_links.txt
influxdb2_dbapi.egg-info/entry_points.txt
influxdb2_dbapi.egg-info/requires.txt
influxdb2_dbapi.egg-info/top_level.txt
tests/test_basic.py